django_models_ext/__init__.py
django_models_ext/basemodels.py
django_models_ext/fileext.py
django_models_ext/provincemodels.py
django_models_ext/queryext.py
django_models_ext-1.1.11.dist-info/METADATA
django_models_ext-1.1.11.dist-info/WHEEL
django_models_ext-1.1.11.dist-info/top_level.txt
django_models_ext-1.1.11.dist-info/RECORD
