Metadata-Version: 2.1
Name: django-models-ext
Version: 1.1.11
Summary: Django Models Extensions
Home-page: https://github.com/django-xxx/django-models-extensions
Author: Hackathon
Author-email: kimi.huang@brightcells.com
Keywords: Django Models Ext Extensions
Classifier: Development Status :: 5 - Production/Stable
Classifier: Environment :: Web Environment
Classifier: Framework :: Django
Classifier: Intended Audience :: Developers
Classifier: Programming Language :: Python
Classifier: Topic :: Software Development :: Libraries :: Python Modules
Classifier: Topic :: Office/Business :: Financial :: Spreadsheet
Requires-Dist: TimeConvert
Requires-Dist: django-six
